no_implicit_optional.py
no_implicit_optional-1.4.dist-info/LICENSE
no_implicit_optional-1.4.dist-info/METADATA
no_implicit_optional-1.4.dist-info/WHEEL
no_implicit_optional-1.4.dist-info/entry_points.txt
no_implicit_optional-1.4.dist-info/top_level.txt
no_implicit_optional-1.4.dist-info/RECORD
